<?xml version="1.0" encoding="UTF-8"?><opendata>	<request>http://www.opendata.larochelle.fr/webservice/?service=getData&amp;key=LHE8vyLUbT4DSMNe&amp;db=insee&amp;table=iris_2008&amp;format=xml&amp;limit=5000</request>	<answer>		<status>code=0 message=Success</status>		<data>			<row>				<IRIS>"173000101"</IRIS>				<REG>"54"</REG>				<DEP>"17"</DEP>				<UU2010>"17601"</UU2010>				<COM>"17300"</COM>				<LIBCOM>"La Rochelle"</LIBCOM>				<TRIRIS>"170041"</TRIRIS>				<GRD_QUART>"1730001"</GRD_QUART>				<LIBIRIS>"Centre Marche"</LIBIRIS>				<TYP_IRIS>"H"</TYP_IRIS>				<MODIF_IRIS>"00"</MODIF_IRIS>				<LAB_IRIS>"1"</LAB_IRIS>			</row>			<row>				<IRIS>"173000102"</IRIS>				<REG>"54"</REG>				<DEP>"17"</DEP>				<UU2010>"17601"</UU2010>				<COM>"17300"</COM>				<LIBCOM>"La Rochelle"</LIBCOM>				<TRIRIS>"170041"</TRIRIS>				<GRD_QUART>"1730001"</GRD_QUART>				<LIBIRIS>"Centre Mairie"</LIBIRIS>				<TYP_IRIS>"H"</TYP_IRIS>				<MODIF_IRIS>"00"</MODIF_IRIS>				<LAB_IRIS>"1"</LAB_IRIS>			</row>			<row>				<IRIS>"173000103"</IRIS>				<REG>"54"</REG>				<DEP>"17"</DEP>				<UU2010>"17601"</UU2010>				<COM>"17300"</COM>				<LIBCOM>"La Rochelle"</LIBCOM>				<TRIRIS>"170041"</TRIRIS>				<GRD_QUART>"1730001"</GRD_QUART>				<LIBIRIS>"Centre Prefecture"</LIBIRIS>				<TYP_IRIS>"H"</TYP_IRIS>				<MODIF_IRIS>"00"</MODIF_IRIS>				<LAB_IRIS>"1"</LAB_IRIS>			</row>			<row>				<IRIS>"173000104"</IRIS>				<REG>"54"</REG>				<DEP>"17"</DEP>				<UU2010>"17601"</UU2010>				<COM>"17300"</COM>				<LIBCOM>"La Rochelle"</LIBCOM>				<TRIRIS>"170041"</TRIRIS>				<GRD_QUART>"1730001"</GRD_QUART>				<LIBIRIS>"Centre Hopital"</LIBIRIS>				<TYP_IRIS>"H"</TYP_IRIS>				<MODIF_IRIS>"00"</MODIF_IRIS>				<LAB_IRIS>"1"</LAB_IRIS>			</row>			<row>				<IRIS>"173000201"</IRIS>				<REG>"54"</REG>				<DEP>"17"</DEP>				<UU2010>"17601"</UU2010>				<COM>"17300"</COM>				<LIBCOM>"La Rochelle"</LIBCOM>				<TRIRIS>"170051"</TRIRIS>				<GRD_QUART>"1730002"</GRD_QUART>				<LIBIRIS>"La Genette Parcs"</LIBIRIS>				<TYP_IRIS>"H"</TYP_IRIS>				<MODIF_IRIS>"00"</MODIF_IRIS>				<LAB_IRIS>"1"</LAB_IRIS>			</row>			<row>				<IRIS>"173000202"</IRIS>				<REG>"54"</REG>				<DEP>"17"</DEP>				<UU2010>"17601"</UU2010>				<COM>"17300"</COM>				<LIBCOM>"La Rochelle"</LIBCOM>				<TRIRIS>"170051"</TRIRIS>				<GRD_QUART>"1730002"</GRD_QUART>				<LIBIRIS>"La Genette Le Mail"</LIBIRIS>				<TYP_IRIS>"H"</TYP_IRIS>				<MODIF_IRIS>"00"</MODIF_IRIS>				<LAB_IRIS>"1"</LAB_IRIS>			</row>			<row>				<IRIS>"173000301"</IRIS>				<REG>"54"</REG>				<DEP>"17"</DEP>				<UU2010>"17601"</UU2010>				<COM>"17300"</COM>				<LIBCOM>"La Rochelle"</LIBCOM>				<TRIRIS>"170051"</TRIRIS>				<GRD_QUART>"1730003"</GRD_QUART>				<LIBIRIS>"Port Neuf Est"</LIBIRIS>				<TYP_IRIS>"H"</TYP_IRIS>				<MODIF_IRIS>"00"</MODIF_IRIS>				<LAB_IRIS>"1"</LAB_IRIS>			</row>			<row>				<IRIS>"173000302"</IRIS>				<REG>"54"</REG>				<DEP>"17"</DEP>				<UU2010>"17601"</UU2010>				<COM>"17300"</COM>				<LIBCOM>"La Rochelle"</LIBCOM>				<TRIRIS>"170051"</TRIRIS>				<GRD_QUART>"1730003"</GRD_QUART>				<LIBIRIS>"Port Neuf Ouest"</LIBIRIS>				<TYP_IRIS>"H"</TYP_IRIS>				<MODIF_IRIS>"00"</MODIF_IRIS>				<LAB_IRIS>"1"</LAB_IRIS>			</row>			<row>				<IRIS>"173000401"</IRIS>				<REG>"54"</REG>				<DEP>"17"</DEP>				<UU2010>"17601"</UU2010>				<COM>"17300"</COM>				<LIBCOM>"La Rochelle"</LIBCOM>				<TRIRIS>"170061"</TRIRIS>				<GRD_QUART>"1730004"</GRD_QUART>				<LIBIRIS>"Chef de Baie"</LIBIRIS>				<TYP_IRIS>"A"</TYP_IRIS>				<MODIF_IRIS>"00"</MODIF_IRIS>				<LAB_IRIS>"3"</LAB_IRIS>			</row>			<row>				<IRIS>"173000402"</IRIS>				<REG>"54"</REG>				<DEP>"17"</DEP>				<UU2010>"17601"</UU2010>				<COM>"17300"</COM>				<LIBCOM>"La Rochelle"</LIBCOM>				<TRIRIS>"170061"</TRIRIS>				<GRD_QUART>"1730004"</GRD_QUART>				<LIBIRIS>"La Pallice"</LIBIRIS>				<TYP_IRIS>"H"</TYP_IRIS>				<MODIF_IRIS>"00"</MODIF_IRIS>				<LAB_IRIS>"1"</LAB_IRIS>			</row>			<row>				<IRIS>"173000403"</IRIS>				<REG>"54"</REG>				<DEP>"17"</DEP>				<UU2010>"17601"</UU2010>				<COM>"17300"</COM>				<LIBCOM>"La Rochelle"</LIBCOM>				<TRIRIS>"170061"</TRIRIS>				<GRD_QUART>"1730004"</GRD_QUART>				<LIBIRIS>"Laleu"</LIBIRIS>				<TYP_IRIS>"H"</TYP_IRIS>				<MODIF_IRIS>"00"</MODIF_IRIS>				<LAB_IRIS>"1"</LAB_IRIS>			</row>			<row>				<IRIS>"173000501"</IRIS>				<REG>"54"</REG>				<DEP>"17"</DEP>				<UU2010>"17601"</UU2010>				<COM>"17300"</COM>				<LIBCOM>"La Rochelle"</LIBCOM>				<TRIRIS>"170081"</TRIRIS>				<GRD_QUART>"1730005"</GRD_QUART>				<LIBIRIS>"Mireuil Ouest"</LIBIRIS>				<TYP_IRIS>"H"</TYP_IRIS>				<MODIF_IRIS>"00"</MODIF_IRIS>				<LAB_IRIS>"1"</LAB_IRIS>			</row>			<row>				<IRIS>"173000502"</IRIS>				<REG>"54"</REG>				<DEP>"17"</DEP>				<UU2010>"17601"</UU2010>				<COM>"17300"</COM>				<LIBCOM>"La Rochelle"</LIBCOM>				<TRIRIS>"170071"</TRIRIS>				<GRD_QUART>"1730005"</GRD_QUART>				<LIBIRIS>"Mireuil Chateau d&amp;apos;Eau"</LIBIRIS>				<TYP_IRIS>"H"</TYP_IRIS>				<MODIF_IRIS>"00"</MODIF_IRIS>				<LAB_IRIS>"1"</LAB_IRIS>			</row>			<row>				<IRIS>"173000503"</IRIS>				<REG>"54"</REG>				<DEP>"17"</DEP>				<UU2010>"17601"</UU2010>				<COM>"17300"</COM>				<LIBCOM>"La Rochelle"</LIBCOM>				<TRIRIS>"170071"</TRIRIS>				<GRD_QUART>"1730005"</GRD_QUART>				<LIBIRIS>"Mireuil Est"</LIBIRIS>				<TYP_IRIS>"H"</TYP_IRIS>				<MODIF_IRIS>"00"</MODIF_IRIS>				<LAB_IRIS>"2"</LAB_IRIS>			</row>			<row>				<IRIS>"173000504"</IRIS>				<REG>"54"</REG>				<DEP>"17"</DEP>				<UU2010>"17601"</UU2010>				<COM>"17300"</COM>				<LIBCOM>"La Rochelle"</LIBCOM>				<TRIRIS>"170071"</TRIRIS>				<GRD_QUART>"1730005"</GRD_QUART>				<LIBIRIS>"Mireuil le Parc"</LIBIRIS>				<TYP_IRIS>"H"</TYP_IRIS>				<MODIF_IRIS>"00"</MODIF_IRIS>				<LAB_IRIS>"1"</LAB_IRIS>			</row>			<row>				<IRIS>"173000505"</IRIS>				<REG>"54"</REG>				<DEP>"17"</DEP>				<UU2010>"17601"</UU2010>				<COM>"17300"</COM>				<LIBCOM>"La Rochelle"</LIBCOM>				<TRIRIS>"170081"</TRIRIS>				<GRD_QUART>"1730005"</GRD_QUART>				<LIBIRIS>"Mireuil Europe"</LIBIRIS>				<TYP_IRIS>"H"</TYP_IRIS>				<MODIF_IRIS>"00"</MODIF_IRIS>				<LAB_IRIS>"1"</LAB_IRIS>			</row>			<row>				<IRIS>"173000601"</IRIS>				<REG>"54"</REG>				<DEP>"17"</DEP>				<UU2010>"17601"</UU2010>				<COM>"17300"</COM>				<LIBCOM>"La Rochelle"</LIBCOM>				<TRIRIS>"170081"</TRIRIS>				<GRD_QUART>"1730006"</GRD_QUART>				<LIBIRIS>"Rossignolette-Saint-Maurice"</LIBIRIS>				<TYP_IRIS>"H"</TYP_IRIS>				<MODIF_IRIS>"00"</MODIF_IRIS>				<LAB_IRIS>"1"</LAB_IRIS>			</row>			<row>				<IRIS>"173000602"</IRIS>				<REG>"54"</REG>				<DEP>"17"</DEP>				<UU2010>"17601"</UU2010>				<COM>"17300"</COM>				<LIBCOM>"La Rochelle"</LIBCOM>				<TRIRIS>"170091"</TRIRIS>				<GRD_QUART>"1730006"</GRD_QUART>				<LIBIRIS>"Bel-Air"</LIBIRIS>				<TYP_IRIS>"H"</TYP_IRIS>				<MODIF_IRIS>"00"</MODIF_IRIS>				<LAB_IRIS>"1"</LAB_IRIS>			</row>			<row>				<IRIS>"173000603"</IRIS>				<REG>"54"</REG>				<DEP>"17"</DEP>				<UU2010>"17601"</UU2010>				<COM>"17300"</COM>				<LIBCOM>"La Rochelle"</LIBCOM>				<TRIRIS>"170091"</TRIRIS>				<GRD_QUART>"1730006"</GRD_QUART>				<LIBIRIS>"Fetilly-La Trompette"</LIBIRIS>				<TYP_IRIS>"H"</TYP_IRIS>				<MODIF_IRIS>"00"</MODIF_IRIS>				<LAB_IRIS>"1"</LAB_IRIS>			</row>			<row>				<IRIS>"173000701"</IRIS>				<REG>"54"</REG>				<DEP>"17"</DEP>				<UU2010>"17601"</UU2010>				<COM>"17300"</COM>				<LIBCOM>"La Rochelle"</LIBCOM>				<TRIRIS>"170091"</TRIRIS>				<GRD_QUART>"1730007"</GRD_QUART>				<LIBIRIS>"Le Prieure"</LIBIRIS>				<TYP_IRIS>"H"</TYP_IRIS>				<MODIF_IRIS>"00"</MODIF_IRIS>				<LAB_IRIS>"1"</LAB_IRIS>			</row>			<row>				<IRIS>"173000702"</IRIS>				<REG>"54"</REG>				<DEP>"17"</DEP>				<UU2010>"17601"</UU2010>				<COM>"17300"</COM>				<LIBCOM>"La Rochelle"</LIBCOM>				<TRIRIS>"170101"</TRIRIS>				<GRD_QUART>"1730007"</GRD_QUART>				<LIBIRIS>"Lafond"</LIBIRIS>				<TYP_IRIS>"H"</TYP_IRIS>				<MODIF_IRIS>"00"</MODIF_IRIS>				<LAB_IRIS>"1"</LAB_IRIS>			</row>			<row>				<IRIS>"173000703"</IRIS>				<REG>"54"</REG>				<DEP>"17"</DEP>				<UU2010>"17601"</UU2010>				<COM>"17300"</COM>				<LIBCOM>"La Rochelle"</LIBCOM>				<TRIRIS>"170101"</TRIRIS>				<GRD_QUART>"1730007"</GRD_QUART>				<LIBIRIS>"Beauregard"</LIBIRIS>				<TYP_IRIS>"H"</TYP_IRIS>				<MODIF_IRIS>"00"</MODIF_IRIS>				<LAB_IRIS>"1"</LAB_IRIS>			</row>			<row>				<IRIS>"173000801"</IRIS>				<REG>"54"</REG>				<DEP>"17"</DEP>				<UU2010>"17601"</UU2010>				<COM>"17300"</COM>				<LIBCOM>"La Rochelle"</LIBCOM>				<TRIRIS>"170101"</TRIRIS>				<GRD_QUART>"1730008"</GRD_QUART>				<LIBIRIS>"Saint-Eloi Nord"</LIBIRIS>				<TYP_IRIS>"H"</TYP_IRIS>				<MODIF_IRIS>"00"</MODIF_IRIS>				<LAB_IRIS>"1"</LAB_IRIS>			</row>			<row>				<IRIS>"173000802"</IRIS>				<REG>"54"</REG>				<DEP>"17"</DEP>				<UU2010>"17601"</UU2010>				<COM>"17300"</COM>				<LIBCOM>"La Rochelle"</LIBCOM>				<TRIRIS>"170101"</TRIRIS>				<GRD_QUART>"1730008"</GRD_QUART>				<LIBIRIS>"Saint-Eloi Sud"</LIBIRIS>				<TYP_IRIS>"H"</TYP_IRIS>				<MODIF_IRIS>"00"</MODIF_IRIS>				<LAB_IRIS>"1"</LAB_IRIS>			</row>			<row>				<IRIS>"173000901"</IRIS>				<REG>"54"</REG>				<DEP>"17"</DEP>				<UU2010>"17601"</UU2010>				<COM>"17300"</COM>				<LIBCOM>"La Rochelle"</LIBCOM>				<TRIRIS>"170111"</TRIRIS>				<GRD_QUART>"1730009"</GRD_QUART>				<LIBIRIS>"Petit Marseille-Foire Exposition"</LIBIRIS>				<TYP_IRIS>"H"</TYP_IRIS>				<MODIF_IRIS>"00"</MODIF_IRIS>				<LAB_IRIS>"1"</LAB_IRIS>			</row>			<row>				<IRIS>"173000902"</IRIS>				<REG>"54"</REG>				<DEP>"17"</DEP>				<UU2010>"17601"</UU2010>				<COM>"17300"</COM>				<LIBCOM>"La Rochelle"</LIBCOM>				<TRIRIS>"170111"</TRIRIS>				<GRD_QUART>"1730009"</GRD_QUART>				<LIBIRIS>"Villeneuve des Salines Ouest"</LIBIRIS>				<TYP_IRIS>"H"</TYP_IRIS>				<MODIF_IRIS>"00"</MODIF_IRIS>				<LAB_IRIS>"2"</LAB_IRIS>			</row>			<row>				<IRIS>"173000903"</IRIS>				<REG>"54"</REG>				<DEP>"17"</DEP>				<UU2010>"17601"</UU2010>				<COM>"17300"</COM>				<LIBCOM>"La Rochelle"</LIBCOM>				<TRIRIS>"170111"</TRIRIS>				<GRD_QUART>"1730009"</GRD_QUART>				<LIBIRIS>"Villeneuve des Salines Est"</LIBIRIS>				<TYP_IRIS>"H"</TYP_IRIS>				<MODIF_IRIS>"00"</MODIF_IRIS>				<LAB_IRIS>"1"</LAB_IRIS>			</row>			<row>				<IRIS>"173000904"</IRIS>				<REG>"54"</REG>				<DEP>"17"</DEP>				<UU2010>"17601"</UU2010>				<COM>"17300"</COM>				<LIBCOM>"La Rochelle"</LIBCOM>				<TRIRIS>"170111"</TRIRIS>				<GRD_QUART>"1730009"</GRD_QUART>				<LIBIRIS>"Villeneuve des Salines Lac"</LIBIRIS>				<TYP_IRIS>"H"</TYP_IRIS>				<MODIF_IRIS>"00"</MODIF_IRIS>				<LAB_IRIS>"2"</LAB_IRIS>			</row>			<row>				<IRIS>"173001001"</IRIS>				<REG>"54"</REG>				<DEP>"17"</DEP>				<UU2010>"17601"</UU2010>				<COM>"17300"</COM>				<LIBCOM>"La Rochelle"</LIBCOM>				<TRIRIS>"170121"</TRIRIS>				<GRD_QUART>"1730010"</GRD_QUART>				<LIBIRIS>"Les Minimes Port de Plaisance"</LIBIRIS>				<TYP_IRIS>"H"</TYP_IRIS>				<MODIF_IRIS>"00"</MODIF_IRIS>				<LAB_IRIS>"1"</LAB_IRIS>			</row>			<row>				<IRIS>"173001002"</IRIS>				<REG>"54"</REG>				<DEP>"17"</DEP>				<UU2010>"17601"</UU2010>				<COM>"17300"</COM>				<LIBCOM>"La Rochelle"</LIBCOM>				<TRIRIS>"170121"</TRIRIS>				<GRD_QUART>"1730010"</GRD_QUART>				<LIBIRIS>"Les Minimes Universite"</LIBIRIS>				<TYP_IRIS>"H"</TYP_IRIS>				<MODIF_IRIS>"00"</MODIF_IRIS>				<LAB_IRIS>"1"</LAB_IRIS>			</row>			<row>				<IRIS>"173001003"</IRIS>				<REG>"54"</REG>				<DEP>"17"</DEP>				<UU2010>"17601"</UU2010>				<COM>"17300"</COM>				<LIBCOM>"La Rochelle"</LIBCOM>				<TRIRIS>"170121"</TRIRIS>				<GRD_QUART>"1730010"</GRD_QUART>				<LIBIRIS>"Les Minimes Tasdon"</LIBIRIS>				<TYP_IRIS>"H"</TYP_IRIS>				<MODIF_IRIS>"00"</MODIF_IRIS>				<LAB_IRIS>"1"</LAB_IRIS>			</row>		</data>	</answer></opendata>