<?xml version="1.0" encoding="UTF-8"?><opendata>	<request>http://www.opendata.larochelle.fr/webservice/?service=getData&amp;key=LHE8vyLUbT4DSMNe&amp;db=passeportjeune&amp;table=passeportjeune_01&amp;format=xml&amp;limit=5000</request>	<answer>		<status>code=0 message=Success</status>		<data>			<row>				<chv_annee>""</chv_annee>				<chv_mois>""</chv_mois>				<ac_libelle>"Entrée Palmilud"</ac_libelle>				<chv_nombre>"517"</chv_nombre>			</row>			<row>				<chv_annee>""</chv_annee>				<chv_mois>""</chv_mois>				<ac_libelle>"1 partie de Laser Games"</ac_libelle>				<chv_nombre>"317"</chv_nombre>			</row>			<row>				<chv_annee>""</chv_annee>				<chv_mois>""</chv_mois>				<ac_libelle>"1 partie de Footempo"</ac_libelle>				<chv_nombre>"246"</chv_nombre>			</row>			<row>				<chv_annee>""</chv_annee>				<chv_mois>""</chv_mois>				<ac_libelle>"1 entrée Piscine Lucien Maylin"</ac_libelle>				<chv_nombre>"194"</chv_nombre>			</row>			<row>				<chv_annee>""</chv_annee>				<chv_mois>""</chv_mois>				<ac_libelle>"1 partie de bowling"</ac_libelle>				<chv_nombre>"181"</chv_nombre>			</row>			<row>				<chv_annee>""</chv_annee>				<chv_mois>""</chv_mois>				<ac_libelle>"1 entrée Centre aquatique de Châtelaillon"</ac_libelle>				<chv_nombre>"177"</chv_nombre>			</row>			<row>				<chv_annee>""</chv_annee>				<chv_mois>""</chv_mois>				<ac_libelle>"Moto ou Quad (3 heures)"</ac_libelle>				<chv_nombre>"143"</chv_nombre>			</row>			<row>				<chv_annee>""</chv_annee>				<chv_mois>""</chv_mois>				<ac_libelle>"2 heures lezard créatif"</ac_libelle>				<chv_nombre>"116"</chv_nombre>			</row>			<row>				<chv_annee>""</chv_annee>				<chv_mois>""</chv_mois>				<ac_libelle>"Squash"</ac_libelle>				<chv_nombre>"112"</chv_nombre>			</row>			<row>				<chv_annee>""</chv_annee>				<chv_mois>""</chv_mois>				<ac_libelle>"ACTIVITES SPORTIVES"</ac_libelle>				<chv_nombre>"93"</chv_nombre>			</row>			<row>				<chv_annee>""</chv_annee>				<chv_mois>""</chv_mois>				<ac_libelle>"Atelier Tom pouce"</ac_libelle>				<chv_nombre>"88"</chv_nombre>			</row>			<row>				<chv_annee>""</chv_annee>				<chv_mois>""</chv_mois>				<ac_libelle>"Vertigo parc- laser o&amp;apos;parc-course d&amp;apos;orientation"</ac_libelle>				<chv_nombre>"85"</chv_nombre>			</row>			<row>				<chv_annee>""</chv_annee>				<chv_mois>""</chv_mois>				<ac_libelle>"Initiation dirt Bike"</ac_libelle>				<chv_nombre>"84"</chv_nombre>			</row>			<row>				<chv_annee>""</chv_annee>				<chv_mois>""</chv_mois>				<ac_libelle>"Sortie Canoë"</ac_libelle>				<chv_nombre>"58"</chv_nombre>			</row>			<row>				<chv_annee>""</chv_annee>				<chv_mois>""</chv_mois>				<ac_libelle>"Sortie Stand Up Paddle"</ac_libelle>				<chv_nombre>"56"</chv_nombre>			</row>			<row>				<chv_annee>""</chv_annee>				<chv_mois>""</chv_mois>				<ac_libelle>"1 stage chant"</ac_libelle>				<chv_nombre>"29"</chv_nombre>			</row>			<row>				<chv_annee>""</chv_annee>				<chv_mois>""</chv_mois>				<ac_libelle>"Rocket trampoline"</ac_libelle>				<chv_nombre>"28"</chv_nombre>			</row>			<row>				<chv_annee>""</chv_annee>				<chv_mois>""</chv_mois>				<ac_libelle>"Atelier dominique marion brière"</ac_libelle>				<chv_nombre>"21"</chv_nombre>			</row>			<row>				<chv_annee>""</chv_annee>				<chv_mois>""</chv_mois>				<ac_libelle>"Stage tennis"</ac_libelle>				<chv_nombre>"19"</chv_nombre>			</row>			<row>				<chv_annee>""</chv_annee>				<chv_mois>""</chv_mois>				<ac_libelle>"Atelier cuisine ou jeux de société"</ac_libelle>				<chv_nombre>"19"</chv_nombre>			</row>			<row>				<chv_annee>""</chv_annee>				<chv_mois>""</chv_mois>				<ac_libelle>"1 sortie kayak de mer (2 heures)"</ac_libelle>				<chv_nombre>"19"</chv_nombre>			</row>			<row>				<chv_annee>""</chv_annee>				<chv_mois>""</chv_mois>				<ac_libelle>"Jeux de sociéte"</ac_libelle>				<chv_nombre>"18"</chv_nombre>			</row>			<row>				<chv_annee>""</chv_annee>				<chv_mois>""</chv_mois>				<ac_libelle>"Stage percussions ou danse Africaine"</ac_libelle>				<chv_nombre>"3"</chv_nombre>			</row>			<row>				<chv_annee>""</chv_annee>				<chv_mois>""</chv_mois>				<ac_libelle>"Visite Musée Maritime"</ac_libelle>				<chv_nombre>"3"</chv_nombre>			</row>			<row>				<chv_annee>""</chv_annee>				<chv_mois>""</chv_mois>				<ac_libelle>"Stage Planche à voile ou Catamaran"</ac_libelle>				<chv_nombre>"2"</chv_nombre>			</row>			<row>				<chv_annee>""</chv_annee>				<chv_mois>""</chv_mois>				<ac_libelle>"Stage arts de la rue cirque"</ac_libelle>				<chv_nombre>"2"</chv_nombre>			</row>			<row>				<chv_annee>""</chv_annee>				<chv_mois>""</chv_mois>				<ac_libelle>"Entrée Aquarium"</ac_libelle>				<chv_nombre>"1"</chv_nombre>			</row>			<row>				<chv_annee>""</chv_annee>				<chv_mois>""</chv_mois>				<ac_libelle>"Initiation Equitation"</ac_libelle>				<chv_nombre>"1"</chv_nombre>			</row>			<row>				<chv_annee>""</chv_annee>				<chv_mois>""</chv_mois>				<ac_libelle>"Stage Kayak de Mer"</ac_libelle>				<chv_nombre>"1"</chv_nombre>			</row>			<row>				<chv_annee>""</chv_annee>				<chv_mois>""</chv_mois>				<ac_libelle>"Stage Magie"</ac_libelle>				<chv_nombre>"1"</chv_nombre>			</row>			<row>				<chv_annee>""</chv_annee>				<chv_mois>""</chv_mois>				<ac_libelle>"Initiation Golf"</ac_libelle>				<chv_nombre>"1"</chv_nombre>			</row>			<row>				<chv_annee>""</chv_annee>				<chv_mois>""</chv_mois>				<ac_libelle>"Stage Hip Hop"</ac_libelle>				<chv_nombre>"1"</chv_nombre>			</row>			<row>				<chv_annee>"2011"</chv_annee>				<chv_mois>"12"</chv_mois>				<ac_libelle>"1 partie de bowling"</ac_libelle>				<chv_nombre>"53"</chv_nombre>			</row>			<row>				<chv_annee>"2011"</chv_annee>				<chv_mois>"12"</chv_mois>				<ac_libelle>"1 partie de Laser Games"</ac_libelle>				<chv_nombre>"17"</chv_nombre>			</row>			<row>				<chv_annee>"2011"</chv_annee>				<chv_mois>"12"</chv_mois>				<ac_libelle>"Squash"</ac_libelle>				<chv_nombre>"6"</chv_nombre>			</row>			<row>				<chv_annee>"2011"</chv_annee>				<chv_mois>"10"</chv_mois>				<ac_libelle>"1 partie de bowling"</ac_libelle>				<chv_nombre>"46"</chv_nombre>			</row>			<row>				<chv_annee>"2011"</chv_annee>				<chv_mois>"10"</chv_mois>				<ac_libelle>"Entrée Palmilud"</ac_libelle>				<chv_nombre>"31"</chv_nombre>			</row>			<row>				<chv_annee>"2011"</chv_annee>				<chv_mois>"10"</chv_mois>				<ac_libelle>"1 partie de Laser Games"</ac_libelle>				<chv_nombre>"20"</chv_nombre>			</row>			<row>				<chv_annee>"2011"</chv_annee>				<chv_mois>"10"</chv_mois>				<ac_libelle>"1 entrée Centre aquatique de Châtelaillon"</ac_libelle>				<chv_nombre>"14"</chv_nombre>			</row>			<row>				<chv_annee>"2011"</chv_annee>				<chv_mois>"10"</chv_mois>				<ac_libelle>"Vertigo parc- laser o&amp;apos;parc-course d&amp;apos;orientation"</ac_libelle>				<chv_nombre>"5"</chv_nombre>			</row>			<row>				<chv_annee>"2011"</chv_annee>				<chv_mois>"10"</chv_mois>				<ac_libelle>"ACTIVITES SPORTIVES"</ac_libelle>				<chv_nombre>"3"</chv_nombre>			</row>			<row>				<chv_annee>"2011"</chv_annee>				<chv_mois>"10"</chv_mois>				<ac_libelle>"Squash"</ac_libelle>				<chv_nombre>"3"</chv_nombre>			</row>			<row>				<chv_annee>"2011"</chv_annee>				<chv_mois>"10"</chv_mois>				<ac_libelle>"1 entrée Piscine Lucien Maylin"</ac_libelle>				<chv_nombre>"2"</chv_nombre>			</row>			<row>				<chv_annee>"2011"</chv_annee>				<chv_mois>"10"</chv_mois>				<ac_libelle>"Initiation dirt Bike"</ac_libelle>				<chv_nombre>"1"</chv_nombre>			</row>			<row>				<chv_annee>"2011"</chv_annee>				<chv_mois>"10"</chv_mois>				<ac_libelle>"Moto ou Quad (3 heures)"</ac_libelle>				<chv_nombre>"1"</chv_nombre>			</row>			<row>				<chv_annee>"2011"</chv_annee>				<chv_mois>"10"</chv_mois>				<ac_libelle>"2 heures lezard créatif"</ac_libelle>				<chv_nombre>"1"</chv_nombre>			</row>			<row>				<chv_annee>"2011"</chv_annee>				<chv_mois>"09"</chv_mois>				<ac_libelle>"Entrée Palmilud"</ac_libelle>				<chv_nombre>"40"</chv_nombre>			</row>			<row>				<chv_annee>"2011"</chv_annee>				<chv_mois>"09"</chv_mois>				<ac_libelle>"1 entrée Centre aquatique de Châtelaillon"</ac_libelle>				<chv_nombre>"36"</chv_nombre>			</row>			<row>				<chv_annee>"2011"</chv_annee>				<chv_mois>"09"</chv_mois>				<ac_libelle>"1 partie de bowling"</ac_libelle>				<chv_nombre>"35"</chv_nombre>			</row>			<row>				<chv_annee>"2011"</chv_annee>				<chv_mois>"09"</chv_mois>				<ac_libelle>"1 entrée Piscine Lucien Maylin"</ac_libelle>				<chv_nombre>"32"</chv_nombre>			</row>			<row>				<chv_annee>"2011"</chv_annee>				<chv_mois>"09"</chv_mois>				<ac_libelle>"1 partie de Footempo"</ac_libelle>				<chv_nombre>"32"</chv_nombre>			</row>			<row>				<chv_annee>"2011"</chv_annee>				<chv_mois>"09"</chv_mois>				<ac_libelle>"1 partie de Laser Games"</ac_libelle>				<chv_nombre>"20"</chv_nombre>			</row>			<row>				<chv_annee>"2011"</chv_annee>				<chv_mois>"09"</chv_mois>				<ac_libelle>"Session Skate"</ac_libelle>				<chv_nombre>"16"</chv_nombre>			</row>			<row>				<chv_annee>"2011"</chv_annee>				<chv_mois>"09"</chv_mois>				<ac_libelle>"Initiation dirt Bike"</ac_libelle>				<chv_nombre>"16"</chv_nombre>			</row>			<row>				<chv_annee>"2011"</chv_annee>				<chv_mois>"09"</chv_mois>				<ac_libelle>"Atelier croque d&amp;apos;art d&amp;apos;art"</ac_libelle>				<chv_nombre>"16"</chv_nombre>			</row>			<row>				<chv_annee>"2011"</chv_annee>				<chv_mois>"09"</chv_mois>				<ac_libelle>"Stage Graff"</ac_libelle>				<chv_nombre>"16"</chv_nombre>			</row>			<row>				<chv_annee>"2011"</chv_annee>				<chv_mois>"09"</chv_mois>				<ac_libelle>"Stage Hip Hop"</ac_libelle>				<chv_nombre>"16"</chv_nombre>			</row>			<row>				<chv_annee>"2011"</chv_annee>				<chv_mois>"09"</chv_mois>				<ac_libelle>"Visite Musée Maritime"</ac_libelle>				<chv_nombre>"16"</chv_nombre>			</row>			<row>				<chv_annee>"2011"</chv_annee>				<chv_mois>"09"</chv_mois>				<ac_libelle>"Squash"</ac_libelle>				<chv_nombre>"16"</chv_nombre>			</row>			<row>				<chv_annee>"2011"</chv_annee>				<chv_mois>"09"</chv_mois>				<ac_libelle>"1 sortie kayak de mer (2 heures)"</ac_libelle>				<chv_nombre>"16"</chv_nombre>			</row>			<row>				<chv_annee>"2011"</chv_annee>				<chv_mois>"09"</chv_mois>				<ac_libelle>"Atelier Tom pouce"</ac_libelle>				<chv_nombre>"16"</chv_nombre>			</row>			<row>				<chv_annee>"2011"</chv_annee>				<chv_mois>"09"</chv_mois>				<ac_libelle>"Initiation Equitation"</ac_libelle>				<chv_nombre>"16"</chv_nombre>			</row>			<row>				<chv_annee>"2011"</chv_annee>				<chv_mois>"08"</chv_mois>				<ac_libelle>"Entrée Palmilud"</ac_libelle>				<chv_nombre>"223"</chv_nombre>			</row>			<row>				<chv_annee>"2011"</chv_annee>				<chv_mois>"08"</chv_mois>				<ac_libelle>"1 partie de bowling"</ac_libelle>				<chv_nombre>"209"</chv_nombre>			</row>			<row>				<chv_annee>"2011"</chv_annee>				<chv_mois>"08"</chv_mois>				<ac_libelle>"1 partie de Laser Games"</ac_libelle>				<chv_nombre>"107"</chv_nombre>			</row>			<row>				<chv_annee>"2011"</chv_annee>				<chv_mois>"08"</chv_mois>				<ac_libelle>"1 entrée Centre aquatique de Châtelaillon"</ac_libelle>				<chv_nombre>"95"</chv_nombre>			</row>			<row>				<chv_annee>"2011"</chv_annee>				<chv_mois>"08"</chv_mois>				<ac_libelle>"1 entrée Piscine Lucien Maylin"</ac_libelle>				<chv_nombre>"61"</chv_nombre>			</row>			<row>				<chv_annee>"2011"</chv_annee>				<chv_mois>"08"</chv_mois>				<ac_libelle>"Vertigo parc- laser o&amp;apos;parc-course d&amp;apos;orientation"</ac_libelle>				<chv_nombre>"57"</chv_nombre>			</row>			<row>				<chv_annee>"2011"</chv_annee>				<chv_mois>"08"</chv_mois>				<ac_libelle>"Squash"</ac_libelle>				<chv_nombre>"18"</chv_nombre>			</row>			<row>				<chv_annee>"2011"</chv_annee>				<chv_mois>"08"</chv_mois>				<ac_libelle>"Rocket trampoline"</ac_libelle>				<chv_nombre>"11"</chv_nombre>			</row>			<row>				<chv_annee>"2011"</chv_annee>				<chv_mois>"08"</chv_mois>				<ac_libelle>"Sortie Stand Up Paddle"</ac_libelle>				<chv_nombre>"9"</chv_nombre>			</row>			<row>				<chv_annee>"2011"</chv_annee>				<chv_mois>"08"</chv_mois>				<ac_libelle>"Moto ou Quad (3 heures)"</ac_libelle>				<chv_nombre>"8"</chv_nombre>			</row>			<row>				<chv_annee>"2011"</chv_annee>				<chv_mois>"08"</chv_mois>				<ac_libelle>"Initiation dirt Bike"</ac_libelle>				<chv_nombre>"7"</chv_nombre>			</row>			<row>				<chv_annee>"2011"</chv_annee>				<chv_mois>"08"</chv_mois>				<ac_libelle>"1 partie de Footempo"</ac_libelle>				<chv_nombre>"6"</chv_nombre>			</row>			<row>				<chv_annee>"2011"</chv_annee>				<chv_mois>"08"</chv_mois>				<ac_libelle>"2 heures lezard créatif"</ac_libelle>				<chv_nombre>"5"</chv_nombre>			</row>			<row>				<chv_annee>"2011"</chv_annee>				<chv_mois>"08"</chv_mois>				<ac_libelle>"Sortie Canoë"</ac_libelle>				<chv_nombre>"4"</chv_nombre>			</row>			<row>				<chv_annee>"2011"</chv_annee>				<chv_mois>"07"</chv_mois>				<ac_libelle>"Entrée Palmilud"</ac_libelle>				<chv_nombre>"482"</chv_nombre>			</row>			<row>				<chv_annee>"2011"</chv_annee>				<chv_mois>"07"</chv_mois>				<ac_libelle>"1 partie de bowling"</ac_libelle>				<chv_nombre>"365"</chv_nombre>			</row>			<row>				<chv_annee>"2011"</chv_annee>				<chv_mois>"07"</chv_mois>				<ac_libelle>"1 partie de Laser Games"</ac_libelle>				<chv_nombre>"171"</chv_nombre>			</row>			<row>				<chv_annee>"2011"</chv_annee>				<chv_mois>"07"</chv_mois>				<ac_libelle>"1 entrée Centre aquatique de Châtelaillon"</ac_libelle>				<chv_nombre>"147"</chv_nombre>			</row>			<row>				<chv_annee>"2011"</chv_annee>				<chv_mois>"07"</chv_mois>				<ac_libelle>"Vertigo parc- laser o&amp;apos;parc-course d&amp;apos;orientation"</ac_libelle>				<chv_nombre>"82"</chv_nombre>			</row>			<row>				<chv_annee>"2011"</chv_annee>				<chv_mois>"07"</chv_mois>				<ac_libelle>"1 partie de Footempo"</ac_libelle>				<chv_nombre>"47"</chv_nombre>			</row>			<row>				<chv_annee>"2011"</chv_annee>				<chv_mois>"07"</chv_mois>				<ac_libelle>"Squash"</ac_libelle>				<chv_nombre>"38"</chv_nombre>			</row>			<row>				<chv_annee>"2011"</chv_annee>				<chv_mois>"07"</chv_mois>				<ac_libelle>"Moto ou Quad (3 heures)"</ac_libelle>				<chv_nombre>"32"</chv_nombre>			</row>			<row>				<chv_annee>"2011"</chv_annee>				<chv_mois>"07"</chv_mois>				<ac_libelle>"Rocket trampoline"</ac_libelle>				<chv_nombre>"27"</chv_nombre>			</row>			<row>				<chv_annee>"2011"</chv_annee>				<chv_mois>"07"</chv_mois>				<ac_libelle>"2 heures lezard créatif"</ac_libelle>				<chv_nombre>"20"</chv_nombre>			</row>			<row>				<chv_annee>"2011"</chv_annee>				<chv_mois>"07"</chv_mois>				<ac_libelle>"Sortie Canoë"</ac_libelle>				<chv_nombre>"17"</chv_nombre>			</row>			<row>				<chv_annee>"2011"</chv_annee>				<chv_mois>"07"</chv_mois>				<ac_libelle>"Initiation dirt Bike"</ac_libelle>				<chv_nombre>"7"</chv_nombre>			</row>			<row>				<chv_annee>"2011"</chv_annee>				<chv_mois>"07"</chv_mois>				<ac_libelle>"1 entrée Piscine Lucien Maylin"</ac_libelle>				<chv_nombre>"6"</chv_nombre>			</row>			<row>				<chv_annee>"2011"</chv_annee>				<chv_mois>"07"</chv_mois>				<ac_libelle>"Sortie Stand Up Paddle"</ac_libelle>				<chv_nombre>"4"</chv_nombre>			</row>			<row>				<chv_annee>"2011"</chv_annee>				<chv_mois>"06"</chv_mois>				<ac_libelle>"Entrée Palmilud"</ac_libelle>				<chv_nombre>"851"</chv_nombre>			</row>			<row>				<chv_annee>"2011"</chv_annee>				<chv_mois>"06"</chv_mois>				<ac_libelle>"1 entrée Centre aquatique de Châtelaillon"</ac_libelle>				<chv_nombre>"815"</chv_nombre>			</row>			<row>				<chv_annee>"2011"</chv_annee>				<chv_mois>"06"</chv_mois>				<ac_libelle>"1 entrée Piscine Lucien Maylin"</ac_libelle>				<chv_nombre>"802"</chv_nombre>			</row>			<row>				<chv_annee>"2011"</chv_annee>				<chv_mois>"06"</chv_mois>				<ac_libelle>"1 partie de bowling"</ac_libelle>				<chv_nombre>"668"</chv_nombre>			</row>			<row>				<chv_annee>"2011"</chv_annee>				<chv_mois>"06"</chv_mois>				<ac_libelle>"1 partie de Laser Games"</ac_libelle>				<chv_nombre>"414"</chv_nombre>			</row>			<row>				<chv_annee>"2011"</chv_annee>				<chv_mois>"06"</chv_mois>				<ac_libelle>"Atelier cuisine ou jeux de société"</ac_libelle>				<chv_nombre>"337"</chv_nombre>			</row>			<row>				<chv_annee>"2011"</chv_annee>				<chv_mois>"06"</chv_mois>				<ac_libelle>"Visite Musée Maritime"</ac_libelle>				<chv_nombre>"301"</chv_nombre>			</row>			<row>				<chv_annee>"2011"</chv_annee>				<chv_mois>"06"</chv_mois>				<ac_libelle>"Stage percussions ou danse Africaine"</ac_libelle>				<chv_nombre>"297"</chv_nombre>			</row>			<row>				<chv_annee>"2011"</chv_annee>				<chv_mois>"06"</chv_mois>				<ac_libelle>"1 partie de Footempo"</ac_libelle>				<chv_nombre>"293"</chv_nombre>			</row>			<row>				<chv_annee>"2011"</chv_annee>				<chv_mois>"06"</chv_mois>				<ac_libelle>"Vertigo parc- laser o&amp;apos;parc-course d&amp;apos;orientation"</ac_libelle>				<chv_nombre>"268"</chv_nombre>			</row>			<row>				<chv_annee>"2011"</chv_annee>				<chv_mois>"06"</chv_mois>				<ac_libelle>"Sortie Canoë"</ac_libelle>				<chv_nombre>"221"</chv_nombre>			</row>			<row>				<chv_annee>"2011"</chv_annee>				<chv_mois>"06"</chv_mois>				<ac_libelle>"Stage arts de la rue cirque"</ac_libelle>				<chv_nombre>"198"</chv_nombre>			</row>			<row>				<chv_annee>"2011"</chv_annee>				<chv_mois>"06"</chv_mois>				<ac_libelle>"1 sortie kayak de mer (2 heures)"</ac_libelle>				<chv_nombre>"182"</chv_nombre>			</row>			<row>				<chv_annee>"2011"</chv_annee>				<chv_mois>"06"</chv_mois>				<ac_libelle>"Initiation Golf"</ac_libelle>				<chv_nombre>"159"</chv_nombre>			</row>			<row>				<chv_annee>"2011"</chv_annee>				<chv_mois>"06"</chv_mois>				<ac_libelle>"Moto ou Quad (3 heures)"</ac_libelle>				<chv_nombre>"125"</chv_nombre>			</row>			<row>				<chv_annee>"2011"</chv_annee>				<chv_mois>"06"</chv_mois>				<ac_libelle>"ACTIVITES SPORTIVES"</ac_libelle>				<chv_nombre>"120"</chv_nombre>			</row>			<row>				<chv_annee>"2011"</chv_annee>				<chv_mois>"06"</chv_mois>				<ac_libelle>"Atelier dominique marion brière"</ac_libelle>				<chv_nombre>"119"</chv_nombre>			</row>			<row>				<chv_annee>"2011"</chv_annee>				<chv_mois>"06"</chv_mois>				<ac_libelle>"Stage Planche à voile ou Catamaran"</ac_libelle>				<chv_nombre>"118"</chv_nombre>			</row>			<row>				<chv_annee>"2011"</chv_annee>				<chv_mois>"06"</chv_mois>				<ac_libelle>"Initiation dirt Bike"</ac_libelle>				<chv_nombre>"105"</chv_nombre>			</row>			<row>				<chv_annee>"2011"</chv_annee>				<chv_mois>"06"</chv_mois>				<ac_libelle>"Session Skate"</ac_libelle>				<chv_nombre>"104"</chv_nombre>			</row>			<row>				<chv_annee>"2011"</chv_annee>				<chv_mois>"06"</chv_mois>				<ac_libelle>"Atelier Tom pouce"</ac_libelle>				<chv_nombre>"104"</chv_nombre>			</row>			<row>				<chv_annee>"2011"</chv_annee>				<chv_mois>"06"</chv_mois>				<ac_libelle>"Initiation Equitation"</ac_libelle>				<chv_nombre>"103"</chv_nombre>			</row>			<row>				<chv_annee>"2011"</chv_annee>				<chv_mois>"06"</chv_mois>				<ac_libelle>"Stage Hip Hop"</ac_libelle>				<chv_nombre>"103"</chv_nombre>			</row>			<row>				<chv_annee>"2011"</chv_annee>				<chv_mois>"06"</chv_mois>				<ac_libelle>"Rocket trampoline"</ac_libelle>				<chv_nombre>"101"</chv_nombre>			</row>			<row>				<chv_annee>"2011"</chv_annee>				<chv_mois>"06"</chv_mois>				<ac_libelle>"Sortie Stand Up Paddle"</ac_libelle>				<chv_nombre>"81"</chv_nombre>			</row>			<row>				<chv_annee>"2011"</chv_annee>				<chv_mois>"06"</chv_mois>				<ac_libelle>"Stage tennis"</ac_libelle>				<chv_nombre>"80"</chv_nombre>			</row>			<row>				<chv_annee>"2011"</chv_annee>				<chv_mois>"06"</chv_mois>				<ac_libelle>"Stage Voile Dériveur 4.20"</ac_libelle>				<chv_nombre>"80"</chv_nombre>			</row>			<row>				<chv_annee>"2011"</chv_annee>				<chv_mois>"06"</chv_mois>				<ac_libelle>"Stage Magie"</ac_libelle>				<chv_nombre>"79"</chv_nombre>			</row>			<row>				<chv_annee>"2011"</chv_annee>				<chv_mois>"06"</chv_mois>				<ac_libelle>"Stage Kayak de Mer"</ac_libelle>				<chv_nombre>"79"</chv_nombre>			</row>			<row>				<chv_annee>"2011"</chv_annee>				<chv_mois>"06"</chv_mois>				<ac_libelle>"Squash"</ac_libelle>				<chv_nombre>"72"</chv_nombre>			</row>			<row>				<chv_annee>"2011"</chv_annee>				<chv_mois>"06"</chv_mois>				<ac_libelle>"Stage Théâtre"</ac_libelle>				<chv_nombre>"60"</chv_nombre>			</row>			<row>				<chv_annee>"2011"</chv_annee>				<chv_mois>"06"</chv_mois>				<ac_libelle>"1 stage chant"</ac_libelle>				<chv_nombre>"60"</chv_nombre>			</row>			<row>				<chv_annee>"2011"</chv_annee>				<chv_mois>"06"</chv_mois>				<ac_libelle>"2 heures lezard créatif"</ac_libelle>				<chv_nombre>"41"</chv_nombre>			</row>			<row>				<chv_annee>"2011"</chv_annee>				<chv_mois>"06"</chv_mois>				<ac_libelle>"Atelier traitement de l&amp;apos;image"</ac_libelle>				<chv_nombre>"40"</chv_nombre>			</row>			<row>				<chv_annee>"2011"</chv_annee>				<chv_mois>"06"</chv_mois>				<ac_libelle>"Atelier two Strike"</ac_libelle>				<chv_nombre>"40"</chv_nombre>			</row>			<row>				<chv_annee>"2011"</chv_annee>				<chv_mois>"06"</chv_mois>				<ac_libelle>"Stage Vidéo Clip"</ac_libelle>				<chv_nombre>"40"</chv_nombre>			</row>			<row>				<chv_annee>"2011"</chv_annee>				<chv_mois>"06"</chv_mois>				<ac_libelle>"Atelier croque d&amp;apos;art d&amp;apos;art"</ac_libelle>				<chv_nombre>"24"</chv_nombre>			</row>			<row>				<chv_annee>"2011"</chv_annee>				<chv_mois>"06"</chv_mois>				<ac_libelle>"Stage Graff"</ac_libelle>				<chv_nombre>"24"</chv_nombre>			</row>			<row>				<chv_annee>"2011"</chv_annee>				<chv_mois>"04"</chv_mois>				<ac_libelle>"Entrée Palmilud"</ac_libelle>				<chv_nombre>"93"</chv_nombre>			</row>			<row>				<chv_annee>"2011"</chv_annee>				<chv_mois>"04"</chv_mois>				<ac_libelle>"1 partie de bowling"</ac_libelle>				<chv_nombre>"87"</chv_nombre>			</row>			<row>				<chv_annee>"2011"</chv_annee>				<chv_mois>"04"</chv_mois>				<ac_libelle>"1 entrée Centre aquatique de Châtelaillon"</ac_libelle>				<chv_nombre>"40"</chv_nombre>			</row>			<row>				<chv_annee>"2011"</chv_annee>				<chv_mois>"04"</chv_mois>				<ac_libelle>"1 partie de Laser Games"</ac_libelle>				<chv_nombre>"30"</chv_nombre>			</row>			<row>				<chv_annee>"2011"</chv_annee>				<chv_mois>"04"</chv_mois>				<ac_libelle>"1 entrée Piscine Lucien Maylin"</ac_libelle>				<chv_nombre>"27"</chv_nombre>			</row>			<row>				<chv_annee>"2011"</chv_annee>				<chv_mois>"04"</chv_mois>				<ac_libelle>"Vertigo parc- laser o&amp;apos;parc-course d&amp;apos;orientation"</ac_libelle>				<chv_nombre>"23"</chv_nombre>			</row>			<row>				<chv_annee>"2011"</chv_annee>				<chv_mois>"04"</chv_mois>				<ac_libelle>"Squash"</ac_libelle>				<chv_nombre>"8"</chv_nombre>			</row>			<row>				<chv_annee>"2011"</chv_annee>				<chv_mois>"04"</chv_mois>				<ac_libelle>"Atelier cuisine ou jeux de société"</ac_libelle>				<chv_nombre>"4"</chv_nombre>			</row>			<row>				<chv_annee>"2011"</chv_annee>				<chv_mois>"04"</chv_mois>				<ac_libelle>"Rocket trampoline"</ac_libelle>				<chv_nombre>"3"</chv_nombre>			</row>			<row>				<chv_annee>"2011"</chv_annee>				<chv_mois>"04"</chv_mois>				<ac_libelle>"1 sortie kayak de mer (2 heures)"</ac_libelle>				<chv_nombre>"3"</chv_nombre>			</row>			<row>				<chv_annee>"2011"</chv_annee>				<chv_mois>"04"</chv_mois>				<ac_libelle>"1 partie de Footempo"</ac_libelle>				<chv_nombre>"2"</chv_nombre>			</row>			<row>				<chv_annee>"2011"</chv_annee>				<chv_mois>"04"</chv_mois>				<ac_libelle>"Jeux de sociéte"</ac_libelle>				<chv_nombre>"2"</chv_nombre>			</row>			<row>				<chv_annee>"2011"</chv_annee>				<chv_mois>"04"</chv_mois>				<ac_libelle>"Moto ou Quad (3 heures)"</ac_libelle>				<chv_nombre>"2"</chv_nombre>			</row>			<row>				<chv_annee>"2011"</chv_annee>				<chv_mois>"04"</chv_mois>				<ac_libelle>"Stage tennis"</ac_libelle>				<chv_nombre>"1"</chv_nombre>			</row>			<row>				<chv_annee>"2011"</chv_annee>				<chv_mois>"04"</chv_mois>				<ac_libelle>"2 heures lezard créatif"</ac_libelle>				<chv_nombre>"1"</chv_nombre>			</row>			<row>				<chv_annee>"2011"</chv_annee>				<chv_mois>"04"</chv_mois>				<ac_libelle>"1 stage chant"</ac_libelle>				<chv_nombre>"1"</chv_nombre>			</row>			<row>				<chv_annee>"2011"</chv_annee>				<chv_mois>"03"</chv_mois>				<ac_libelle>"1 partie de bowling"</ac_libelle>				<chv_nombre>"28"</chv_nombre>			</row>			<row>				<chv_annee>"2011"</chv_annee>				<chv_mois>"03"</chv_mois>				<ac_libelle>"1 partie de Laser Games"</ac_libelle>				<chv_nombre>"25"</chv_nombre>			</row>			<row>				<chv_annee>"2011"</chv_annee>				<chv_mois>"03"</chv_mois>				<ac_libelle>"Entrée Palmilud"</ac_libelle>				<chv_nombre>"13"</chv_nombre>			</row>			<row>				<chv_annee>"2011"</chv_annee>				<chv_mois>"03"</chv_mois>				<ac_libelle>"Moto ou Quad (3 heures)"</ac_libelle>				<chv_nombre>"3"</chv_nombre>			</row>			<row>				<chv_annee>"2011"</chv_annee>				<chv_mois>"03"</chv_mois>				<ac_libelle>"1 entrée Piscine Lucien Maylin"</ac_libelle>				<chv_nombre>"3"</chv_nombre>			</row>			<row>				<chv_annee>"2011"</chv_annee>				<chv_mois>"02"</chv_mois>				<ac_libelle>"1 partie de bowling"</ac_libelle>				<chv_nombre>"70"</chv_nombre>			</row>			<row>				<chv_annee>"2011"</chv_annee>				<chv_mois>"02"</chv_mois>				<ac_libelle>"Entrée Palmilud"</ac_libelle>				<chv_nombre>"37"</chv_nombre>			</row>			<row>				<chv_annee>"2011"</chv_annee>				<chv_mois>"02"</chv_mois>				<ac_libelle>"1 partie de Laser Games"</ac_libelle>				<chv_nombre>"37"</chv_nombre>			</row>			<row>				<chv_annee>"2011"</chv_annee>				<chv_mois>"02"</chv_mois>				<ac_libelle>"1 entrée Centre aquatique de Châtelaillon"</ac_libelle>				<chv_nombre>"10"</chv_nombre>			</row>			<row>				<chv_annee>"2011"</chv_annee>				<chv_mois>"02"</chv_mois>				<ac_libelle>"1 entrée Piscine Lucien Maylin"</ac_libelle>				<chv_nombre>"9"</chv_nombre>			</row>			<row>				<chv_annee>"2011"</chv_annee>				<chv_mois>"02"</chv_mois>				<ac_libelle>"Squash"</ac_libelle>				<chv_nombre>"3"</chv_nombre>			</row>			<row>				<chv_annee>"2011"</chv_annee>				<chv_mois>"02"</chv_mois>				<ac_libelle>"Moto ou Quad (3 heures)"</ac_libelle>				<chv_nombre>"3"</chv_nombre>			</row>			<row>				<chv_annee>"2011"</chv_annee>				<chv_mois>"02"</chv_mois>				<ac_libelle>"2 heures lezard créatif"</ac_libelle>				<chv_nombre>"2"</chv_nombre>			</row>			<row>				<chv_annee>"2011"</chv_annee>				<chv_mois>"02"</chv_mois>				<ac_libelle>"Entrée CGR (par un)"</ac_libelle>				<chv_nombre>"2"</chv_nombre>			</row>			<row>				<chv_annee>"2011"</chv_annee>				<chv_mois>"01"</chv_mois>				<ac_libelle>"Vertigo parc- laser o&amp;apos;parc-course d&amp;apos;orientation"</ac_libelle>				<chv_nombre>"6"</chv_nombre>			</row>			<row>				<chv_annee>"2011"</chv_annee>				<chv_mois>"01"</chv_mois>				<ac_libelle>"Entrée CGR (par un)"</ac_libelle>				<chv_nombre>"3"</chv_nombre>			</row>			<row>				<chv_annee>"2011"</chv_annee>				<chv_mois>"01"</chv_mois>				<ac_libelle>"1 partie de bowling"</ac_libelle>				<chv_nombre>"2"</chv_nombre>			</row>		</data>	</answer></opendata>